LICENSE.txt
MANIFEST.in
README.md
setup.cfg
setup.py
dask.mesos.egg-info/PKG-INFO
dask.mesos.egg-info/SOURCES.txt
dask.mesos.egg-info/dependency_links.txt
dask.mesos.egg-info/not-zip-safe
dask.mesos.egg-info/requires.txt
dask.mesos.egg-info/top_level.txt
dask_mesos/__init__.py
dask_mesos/context.py
dask_mesos/delayed.py
dask_mesos/executor.py
dask_mesos/utils.py
docs/index.rst