Metadata-Version: 1.0
Name: dask.mesos
Version: 0.2.1
Summary: Apache Mesos backend for Dask scheduling library
Home-page: http://github.com/lensacom/dask.mesos
Author: Krisztián Szűcs
Author-email: krisztian.szucs@lensa.com
License: Apache License, Version 2.0
Keywords: mesos dask multiprocessing scheduling satyr
Platform: UNKNOWN
